{
  "project_info": {
    "project_number": "607605761699",
    "firebase_url": "https://tunel-f0f82.firebaseio.com",
    "project_id": "tunel-f0f82",
    "storage_bucket": "tunel-f0f82.appspot.com"
  },
  "client": [
    {
      "client_info": {
        "mobilesdk_app_id": "1:607605761699:android:e02b75edee86c0b2",
        "android_client_info": {
          "package_name": "uk.ac.brunel.tunel"
        }
      },
      "oauth_client": [
        {
          "client_id": "607605761699-375o201be8jcd8j89r8o8912q9npee4r.apps.googleusercontent.com",
          "client_type": 1,
          "android_info": {
            "package_name": "uk.ac.brunel.tunel",
            "certificate_hash": "E701AF17ED46516B6855F523A1285DF136D636F1"
          }
        },
        {
          "client_id": "607605761699-0hq4faji8kkle0de008222t4fr12r8kd.apps.googleusercontent.com",
          "client_type": 3
        }
      ],
      "api_key": [
        {
          "current_key": "AIzaSyDXkDqoanvyRVpTKtzChXLKXMUubB9KC1U"
        }
      ],
      "services": {
        "analytics_service": {
          "status": 1
        },
        "appinvite_service": {
          "status": 2,
          "other_platform_oauth_client": [
            {
              "client_id": "607605761699-0hq4faji8kkle0de008222t4fr12r8kd.apps.googleusercontent.com",
              "client_type": 3
            }
          ]
        },
        "ads_service": {
          "status": 2
        }
      }
    }
  ],
  "configuration_version": "1"
}